{
   "width": "container",
   "height": "container",
   "background": null,
   "config": {
      "axis": {
         "gridColor": "white"
      },
      "axisX": {
         "labelColor": "white",
         "titleColor": "white"
      },
      "axisY": {
         "labelColor": "white",
         "titleColor": "white"
      }
   },
   "data": {
      "name": "data-093ece8c35bb2d41094cfb6138ec810b"
   },
   "mark": "point",
   "encoding": {
      "color": {
         "field": "from file",
         "type": "nominal",
         "legend": null,
         "scale": {
            "domain": [
               "1",
               "2"
            ],
            "range": [
               "lightblue",
               "gold"
            ]
         }
      },
      "tooltip": [
         {
            "field": "from file"
         },
         {
            "field": "yield",
            "type": "quantitative"
         },
         {
            "field": "site",
            "type": "nominal"
         }
      ],
      "x": {
         "field": "yield",
         "type": "quantitative"
      },
      "y": {
         "field": "site",
         "type": "nominal"
      }
   },
   "$schema": "https://vega.github.io/schema/vega-lite/v4.17.0.json",
   "datasets": {
      "data-093ece8c35bb2d41094cfb6138ec810b": [
         {
            "yield": 27,
            "variety": "Manchuria",
            "year": 1931,
            "site": "University Farm",
            "from file": "1"
         },
         {
            "yield": 48.86667,
            "variety": "Manchuria",
            "year": 1931,
            "site": "Waseca",
            "from file": "1"
         },
         {
            "yield": 39.93333,
            "variety": "Manchuria",
            "year": 1931,
            "site": "Crookston",
            "from file": "1"
         },
         {
            "yield": 28.96667,
            "variety": "Manchuria",
            "year": 1931,
            "site": "Duluth",
            "from file": "1"
         },
         {
            "yield": 47.33333,
            "variety": "Svansota",
            "year": 1931,
            "site": "Waseca",
            "from file": "1"
         },
         {
            "yield": 25.76667,
            "variety": "Svansota",
            "year": 1931,
            "site": "Morris",
            "from file": "1"
         },
         {
            "yield": 25.7,
            "variety": "Svansota",
            "year": 1931,
            "site": "Duluth",
            "from file": "1"
         },
         {
            "yield": 50.23333,
            "variety": "Velvet",
            "year": 1931,
            "site": "Waseca",
            "from file": "1"
         },
         {
            "yield": 46.93333,
            "variety": "Trebi",
            "year": 1931,
            "site": "Crookston",
            "from file": "1"
         },
         {
            "yield": 28.7,
            "variety": "No. 457",
            "year": 1931,
            "site": "Morris",
            "from file": "1"
         },
         {
            "yield": 29.86667,
            "variety": "Peatland",
            "year": 1931,
            "site": "Morris",
            "from file": "1"
         },
         {
            "yield": 22.6,
            "variety": "No. 475",
            "year": 1931,
            "site": "Morris",
            "from file": "1"
         },
         {
            "yield": 33.06666,
            "variety": "No. 475",
            "year": 1931,
            "site": "Duluth",
            "from file": "1"
         },
         {
            "yield": 39.3,
            "variety": "Wisconsin No. 38",
            "year": 1931,
            "site": "University Farm",
            "from file": "1"
         },
         {
            "yield": 49.86667,
            "variety": "Wisconsin No. 38",
            "year": 1931,
            "site": "Crookston",
            "from file": "1"
         },
         {
            "yield": 33.46667,
            "variety": "Manchuria",
            "year": 1932,
            "site": "Waseca",
            "from file": "1"
         },
         {
            "yield": 37.73333,
            "variety": "Glabron",
            "year": 1932,
            "site": "Waseca",
            "from file": "1"
         },
         {
            "yield": 35.13333,
            "variety": "Glabron",
            "year": 1932,
            "site": "Morris",
            "from file": "1"
         },
         {
            "yield": 26.16667,
            "variety": "Glabron",
            "year": 1932,
            "site": "Crookston",
            "from file": "1"
         },
         {
            "yield": 35.03333,
            "variety": "Svansota",
            "year": 1932,
            "site": "Morris",
            "from file": "1"
         },
         {
            "yield": 16.63333,
            "variety": "Svansota",
            "year": 1932,
            "site": "Grand Rapids",
            "from file": "1"
         },
         {
            "yield": 26.8,
            "variety": "Velvet",
            "year": 1932,
            "site": "University Farm",
            "from file": "1"
         },
         {
            "yield": 37.4,
            "variety": "Velvet",
            "year": 1932,
            "site": "Waseca",
            "from file": "1"
         },
         {
            "yield": 25.56667,
            "variety": "No. 462",
            "year": 1932,
            "site": "University Farm",
            "from file": "1"
         },
         {
            "yield": 44.7,
            "variety": "No. 462",
            "year": 1932,
            "site": "Waseca",
            "from file": "1"
         },
         {
            "yield": 47,
            "variety": "No. 462",
            "year": 1932,
            "site": "Morris",
            "from file": "1"
         },
         {
            "yield": 36.03333,
            "variety": "Peatland",
            "year": 1932,
            "site": "Waseca",
            "from file": "1"
         },
         {
            "yield": 43.2,
            "variety": "Peatland",
            "year": 1932,
            "site": "Morris",
            "from file": "1"
         },
         {
            "yield": 26.76667,
            "variety": "Peatland",
            "year": 1932,
            "site": "Grand Rapids",
            "from file": "1"
         },
         {
            "yield": 22,
            "variety": "Peatland",
            "year": 1931,
            "site": "Morris",
            "from file": "2"
         },
         {
            "yield": 39.093336,
            "variety": "Manchuria",
            "year": 1931,
            "site": "Waseca",
            "from file": "2"
         },
         {
            "yield": 23,
            "variety": "Wisconsin No. 38",
            "year": 1931,
            "site": "Morris",
            "from file": "2"
         },
         {
            "yield": 43,
            "variety": "Manchuria",
            "year": 1931,
            "site": "Crookston",
            "from file": "2"
         },
         {
            "yield": 28,
            "variety": "Manchuria",
            "year": 1931,
            "site": "Crookston",
            "from file": "2"
         },
         {
            "yield": 40.18,
            "variety": "No. 457",
            "year": 1931,
            "site": "Morris",
            "from file": "2"
         },
         {
            "yield": 64,
            "variety": "No. 462",
            "year": 1931,
            "site": "Morris",
            "from file": "2"
         },
         {
            "yield": 38,
            "variety": "No. 475",
            "year": 1931,
            "site": "Duluth",
            "from file": "2"
         },
         {
            "yield": 31,
            "variety": "No. 462",
            "year": 1931,
            "site": "Morris",
            "from file": "2"
         },
         {
            "yield": 33.959997,
            "variety": "Glabron",
            "year": 1932,
            "site": "Waseca",
            "from file": "2"
         },
         {
            "yield": 52,
            "variety": "No. 475",
            "year": 1931,
            "site": "Waseca",
            "from file": "2"
         },
         {
            "yield": 23.010002999999998,
            "variety": "No. 462",
            "year": 1932,
            "site": "University Farm",
            "from file": "2"
         },
         {
            "yield": 26.820000000000004,
            "variety": "No. 462",
            "year": 1932,
            "site": "Waseca",
            "from file": "2"
         },
         {
            "yield": 23,
            "variety": "No. 462",
            "year": 1932,
            "site": "Morris",
            "from file": "2"
         },
         {
            "yield": 24,
            "variety": "Wisconsin No. 38",
            "year": 1931,
            "site": "Morris",
            "from file": "2"
         },
         {
            "yield": 15,
            "variety": "Svansota",
            "year": 1931,
            "site": "Crookston",
            "from file": "2"
         },
         {
            "yield": 34.796671,
            "variety": "Peatland",
            "year": 1932,
            "site": "Grand Rapids",
            "from file": "2"
         }
      ]
   }
}